garlandtools/__init__.py
garlandtools/client.py
garlandtools/models/__init__.py
garlandtools/models/lang.py
garlandtools/models/partials/__init__.py
garlandtools/models/partials/item_partial.py
garlandtools/models/partials/partial.py
garlandtools/models/records/base_record.py
garlandtools/models/records/factory.py
garlandtools/models/records/item.py
garlandtools/models/type.py
garlandtools_async-0.3.0.dist-info/LICENSE
garlandtools_async-0.3.0.dist-info/METADATA
garlandtools_async-0.3.0.dist-info/WHEEL
garlandtools_async-0.3.0.dist-info/RECORD
