Metadata-Version: 2.1
Name: garlandtools-async
Version: 0.3.0
Summary: A async python wrapper for the https://garlandtools.org/ API
License: MIT
Author: Abigail Howe
Author-email: abby@abigailhowe.org
Requires-Python: >=3.10,<4.0
Classifier: License :: OSI Approved :: MIT License
Classifier: Programming Language :: Python :: 3
Classifier: Programming Language :: Python :: 3.10
Classifier: Programming Language :: Python :: 3.11
Requires-Dist: aiohttp (>=3.8.4,<4.0.0)
Requires-Dist: cachetools (>=5.3.1,<6.0.0)
Requires-Dist: shelved-cache (>=0.3.1,<0.4.0)
